conda_share/__init__.py
conda_share/conda_share.cpython-314-x86_64-linux-musl.so
conda_share-2.0.3.dist-info/METADATA
conda_share-2.0.3.dist-info/WHEEL
conda_share.libs/libgcc_s-6d2d9dc8.so.1
conda_share-2.0.3.dist-info/RECORD
