Metadata-Version: 2.4
Name: conda-share
Version: 2.0.3
Summary: Easily share conda environments.
Keywords: conda,environment,sharing,python,package,dependency,data science,reproducibility
Author-email: James Bruska <bruskatech@protonmail.com>
License-Expression: GPL-3.0-or-later
